html2excel/__init__.py
html2excel/__main__.py
html2excel/base/__init__.py
html2excel/base/parser.py
html2excel/excel/__init__.py
html2excel/excel/parser.py
html2excel-0.0.6.dist-info/LICENSE
html2excel-0.0.6.dist-info/METADATA
html2excel-0.0.6.dist-info/WHEEL
html2excel-0.0.6.dist-info/top_level.txt
html2excel-0.0.6.dist-info/RECORD
