Metadata-Version: 2.1
Name: html2excel
Version: 0.0.6
Summary: Convert HTML Table to Excel file
Home-page: https://github.com/Annmayn/html2excel
Author: Neema Tsering
Author-email: ntvirus333@gmail.com
License: MIT
Platform: UNKNOWN
Requires-Dist: bs4
Requires-Dist: openpyxl
Requires-Dist: html5lib
